tkit/__init__.py
tkit/jsonparser.py
tkit/pinyinutils.py
tkit/urlsign.py
tkit-0.1.1.dist-info/licenses/LICENSE
tkit-0.1.1.dist-info/METADATA
tkit-0.1.1.dist-info/WHEEL
tkit-0.1.1.dist-info/top_level.txt
tkit-0.1.1.dist-info/RECORD
